{"sector":{"0":"Consumer Defensive"},"longName":{"0":"Balrampur Chini Mills Limited"},"fullTimeEmployees":{"0":6350},"longBusinessSummary":{"0":"Balrampur Chini Mills Limited, an integrated sugar manufacturing company, manufactures and sells sugar in India. It operates through Sugar, Co-generation, and Distillery segments. The company also offers molasses, press mud, industrial alcohol, ethanol, and bagasse; and agricultural fertilizers, such as soil conditioner, granulated potash, etc. In addition, it is involved in the generation and sale of electricity. The company was incorporated in 1975 and is headquartered in Kolkata, India."},"city":{"0":"Kolkata"},"phone":{"0":"91 33 2287 4749"},"website":{"0":"https:\/\/www.chini.com"},"grossProfits":{"0":13110456000},"totalCash":{"0":1756280064},"totalDebt":{"0":4812125184},"totalRevenue":{"0":46849363968},"totalCashPerShare":{"0":8.608},"revenuePerShare":{"0":229.181},"bookValue":{"0":134.566},"priceToBook":{"0":2.9483674},"marketCap":{"0":80927080448},"averageVolume":{"0":2478698},"fiftyTwoWeekHigh":{"0":525.9},"fiftyTwoWeekLow":{"0":307.3},"logo_url":{"0":"https:\/\/logo.clearbit.com\/chini.com"}}