{"sector":{"0":"Utilities"},"longName":{"0":"CESC Limited"},"fullTimeEmployees":{"0":6920},"longBusinessSummary":{"0":"CESC Limited, an integrated electrical utility company, engages in the generation and distribution of electricity in India. It owns and operates three thermal power plants, including Budge Budge, Southern, and Titagarh generating stations generating 1125 megawatts (MW) of power; a thermal power project with a capacity of 600 MW in Haldia, West Bengal; two thermal power projects with a capacity of 600 MW in Chandrapur, Maharashtra and 40 MW atmospheric fluidized bed combustion power plant in Asansol, West Bengal; and transmission and distribution network of 23468 circuit kms, and distributes power in Uttar Pradesh with license area of 335 square kilometers. The company also owns and operates solar power project with a capacity of 18 MW data center in Ramanathapuram, Tamil Nadu. It serves approximately 3.5 million domestic, industrial, and commercial users in 567 square kilometers of Kolkata and Howrah. CESC Limited was founded in 1899 and is headquartered in Kolkata, India."},"city":{"0":"Kolkata"},"phone":{"0":"91 33 2225 6040"},"website":{"0":"https:\/\/www.cesc.co.in"},"grossProfits":{"0":54726800000},"totalCash":{"0":34720100352},"totalDebt":{"0":149608005632},"totalRevenue":{"0":134298796032},"totalCashPerShare":{"0":26.193},"revenuePerShare":{"0":101.397},"bookValue":{"0":759.454},"priceToBook":{"0":0.100598596},"marketCap":{"0":101273550848},"averageVolume":{"0":1807259},"fiftyTwoWeekHigh":{"0":94.5},"fiftyTwoWeekLow":{"0":68},"logo_url":{"0":"https:\/\/logo.clearbit.com\/cesc.co.in"}}