{"sector":{"0":"Consumer Cyclical"},"longName":{"0":"Devyani International Limited"},"fullTimeEmployees":{"0":13020},"longBusinessSummary":{"0":"Devyani International Limited operates a chain of franchised quick service restaurants in India, Nepal, and Nigeria. The company's Core Brands Business include KFC, Pizza Hut, and Costa Coffee stores operated in India; International Business comprise KFC and Pizza Hut stores operated in Nepal and Nigeria; and Other Business consists of its own brands, such as Vaango, Food Street, Masala Twist, Ile Bar, Amreli, and Ckrussh Juice Bar. As of March 31, 2022, it operated 605 stores, including g 364 KFC stores, 413 Pizza Hut stores, and 55 Costa Coffee stores; and Other Business operated 50 stores. The company was incorporated in 1991 and is based in Gurugram, India. Devyani International Limited is a subsidiary of RJ Corp Limited."},"city":{"0":"Gurugram"},"phone":{"0":"91 12 4478 6000"},"website":{"0":"https:\/\/www.dil-rjcorp.com"},"grossProfits":{"0":11637060000},"totalCash":{"0":1495580032},"totalDebt":{"0":12542260224},"totalRevenue":{"0":24359800832},"totalCashPerShare":{"0":1.241},"revenuePerShare":{"0":20.32},"bookValue":{"0":4.549},"priceToBook":{"0":39.73401},"marketCap":{"0":217355501568},"averageVolume":{"0":2352471},"fiftyTwoWeekHigh":{"0":215},"fiftyTwoWeekLow":{"0":141},"logo_url":{"0":"https:\/\/logo.clearbit.com\/dil-rjcorp.com"}}