{"sector":{"0":"Communication Services"},"longName":{"0":"INOX Leisure Limited"},"fullTimeEmployees":{"0":1488},"longBusinessSummary":{"0":"INOX Leisure Limited operates and manages multiplexes and cinema theatres under the INOX brand name in India. As of August 3, 2022, it operated 163 multiplexes and 692 screens in 73 cities. The company was incorporated in 1999 and is based in Mumbai, India."},"city":{"0":"Mumbai"},"phone":{"0":"91 22 4062 6900"},"website":{"0":"https:\/\/www.inoxmovies.com"},"grossProfits":{"0":4168399000},"totalCash":{"0":1910300032},"totalDebt":{"0":30436999168},"totalRevenue":{"0":15705680896},"totalCashPerShare":{"0":15.616},"revenuePerShare":{"0":128.638},"bookValue":{"0":56.545},"priceToBook":{"0":8.835442},"marketCap":{"0":58963791872},"averageVolume":{"0":298579},"fiftyTwoWeekHigh":{"0":619.35},"fiftyTwoWeekLow":{"0":344.6},"logo_url":{"0":"https:\/\/logo.clearbit.com\/inoxmovies.com"}}