{"sector":{"0":"Utilities"},"longName":{"0":"Mahanagar Gas Limited"},"fullTimeEmployees":{"0":491},"longBusinessSummary":{"0":"Mahanagar Gas Limited operates as a natural gas distribution company in India. The company provides domestic piped natural gas (PNG), commercial PNG, industrial PNG, and compressed natural gas (CNG), as well as manufactures gas geysers. It operates 290 CNG filing stations that provides gas to approximately 8.5 lakh vehicles with 1,738 dispensing points; 550 km of steel pipeline and approximately 5,670 km of MDPE pipeline; and 4,339 commercial and industrial customers. The company's PNG is used for various applications, such as cooking and water heating, as well as in hospitals, nursing homes, hotels, flight kitchens, restaurants, places of worship, etc. Mahanagar Gas Limited was incorporated in 1995 and is based in Mumbai, India."},"city":{"0":"Mumbai"},"phone":{"0":"91 22 6678 5000"},"website":{"0":"https:\/\/www.mahanagargas.com"},"grossProfits":{"0":14343528000},"totalCash":{"0":15491790848},"totalDebt":{"0":1029884032},"totalRevenue":{"0":43994443776},"totalCashPerShare":{"0":156.835},"revenuePerShare":{"0":445.396},"bookValue":{"0":292.475},"priceToBook":{"0":2.866057},"marketCap":{"0":82800492544},"averageVolume":{"0":453911},"fiftyTwoWeekHigh":{"0":925},"fiftyTwoWeekLow":{"0":665.8},"logo_url":{"0":"https:\/\/logo.clearbit.com\/mahanagargas.com"}}